README.md
setup.py
SmallGoogleTranslator.egg-info/PKG-INFO
SmallGoogleTranslator.egg-info/SOURCES.txt
SmallGoogleTranslator.egg-info/dependency_links.txt
SmallGoogleTranslator.egg-info/top_level.txt
google/__init__.py
google/translator.py