Metadata-Version: 2.1
Name: SmallGoogleTranslator
Version: 1.1
Summary: Использование гугл-переводчика удобным вам образом.
Home-page: https://github.com/MagM1go/GoogleTranslator
Author: MagMigo
License: UNKNOWN
Platform: UNKNOWN
Classifier: Programming Language :: Python :: 3.10
Classifier: License :: OSI Approved :: MIT License
Classifier: Operating System :: OS Independent
Requires-Python: >=3.6
